README.md
setup.py
unibot/__init__.py
unibot/main.py
unibot.egg-info/PKG-INFO
unibot.egg-info/SOURCES.txt
unibot.egg-info/dependency_links.txt
unibot.egg-info/top_level.txt