Metadata-Version: 2.1
Name: unibot
Version: 0.0.0.3.1
Summary: UNKNOWN
Home-page: https://github.com/ShaonMajumder/unibot
Author: Shaon Majumder
Author-email: smazoomder@gmail.com
License: UNKNOWN
Download-URL: https://github.com/ShaonMajumder/unibot/archive/0.0.0.3.1.tar.gz
Keywords: shaon,utility,statistics
Platform: UNKNOWN
